cotkg_ids/__init__.py
cotkg_ids/main.py
cotkg_ids/model_test.py
cotkg_ids/test.py
cotkg_ids/train.py
cotkg_ids/config/config.py
cotkg_ids/config/test_config.py
cotkg_ids/data_processing/__init__.py
cotkg_ids/data_processing/data_balancing.py
cotkg_ids/data_processing/feature_engineering.py
cotkg_ids/data_processing/feature_selection.py
cotkg_ids/data_processing/preprocess.py
cotkg_ids/evaluation/__init__.py
cotkg_ids/evaluation/metrics.py
cotkg_ids/explainability/__init__.py
cotkg_ids/explainability/explanation_generator.py
cotkg_ids/explainability/integrated_gradients.py
cotkg_ids/explainability/subgraph_matcher.py
cotkg_ids/knowledge_graph/__init__.py
cotkg_ids/knowledge_graph/cot_generator.py
cotkg_ids/knowledge_graph/kg_analysis.py
cotkg_ids/knowledge_graph/kg_constructor.py
cotkg_ids/knowledge_graph/kg_updater.py
cotkg_ids/models/__init__.py
cotkg_ids/models/gnn_model.py
cotkg_ids/models/graph_sage_model.py
cotkg_ids/models/graph_sage_prep.py
cotkg_ids/models/hybrid_model.py
cotkg_ids/scripts/__init__.py
cotkg_ids/scripts/setup_ollama.py
cotkg_ids/visualization/__init__.py
cotkg_ids/visualization/kg_visualizer.py
cotkg_ids/visualization/visualizer.py
cotkg_ids-0.2.3.dist-info/LICENSE
cotkg_ids-0.2.3.dist-info/METADATA
cotkg_ids-0.2.3.dist-info/WHEEL
cotkg_ids-0.2.3.dist-info/entry_points.txt
cotkg_ids-0.2.3.dist-info/top_level.txt
cotkg_ids-0.2.3.dist-info/RECORD
