Metadata-Version: 2.2
Name: cotkg-ids
Version: 0.2.3
Summary: A network intrusion detection system using Chain of Thought, knowledge graphs and GraphSAGE
Home-page: https://github.com/chenxingqiang/cotkg-network-intrusion-detection
Author: Chen Xingqiang
Author-email: chen.xingqiang@iechor.com
Project-URL: Bug Tracker, https://github.com/chenxingqiang/cotkg-network-intrusion-detection/issues
Project-URL: Documentation, https://github.com/chenxingqiang/cotkg-network-intrusion-detection/wiki
Project-URL: Source Code, https://github.com/chenxingqiang/cotkg-network-intrusion-detection
Classifier: Development Status :: 3 - Alpha
Classifier: Intended Audience :: Developers
Classifier: Intended Audience :: Science/Research
Classifier: License :: OSI Approved :: MIT License
Classifier: Operating System :: OS Independent
Classifier: Programming Language :: Python :: 3
Classifier: Programming Language :: Python :: 3.7
Classifier: Programming Language :: Python :: 3.8
Classifier: Programming Language :: Python :: 3.9
Classifier: Topic :: Security
Classifier: Topic :: Scientific/Engineering :: Artificial Intelligence
Requires-Python: >=3.7
License-File: LICENSE
Requires-Dist: numpy
Requires-Dist: pandas
Requires-Dist: scikit-learn
Requires-Dist: imbalanced-learn
Requires-Dist: joblib
Requires-Dist: pyarrow
Requires-Dist: torch>=1.9.0
Requires-Dist: torch-geometric
Requires-Dist: networkx
Requires-Dist: py2neo
Requires-Dist: matplotlib
Requires-Dist: seaborn
Requires-Dist: tsfresh
Requires-Dist: shap
Requires-Dist: transformers
Requires-Dist: openai
Requires-Dist: anthropic
Requires-Dist: dashscope
Requires-Dist: zhipuai
Requires-Dist: httpcore[socks]
Requires-Dist: ollama
Requires-Dist: tqdm
Requires-Dist: jupyter==1.0.0
Requires-Dist: pytest
Requires-Dist: requests
Dynamic: author
Dynamic: author-email
Dynamic: classifier
Dynamic: description
Dynamic: description-content-type
Dynamic: home-page
Dynamic: project-url
Dynamic: requires-dist
Dynamic: requires-python
Dynamic: summary
